rorf/__init__.py
rorf/calibrate_threshold.py
rorf/controller.py
rorf/router/__init__.py
rorf/router/dataloader.py
rorf/router/embeddings.py
rorf/router/rorf.py
rorf/router/utils.py
rorf-0.1.3.dist-info/LICENSE
rorf-0.1.3.dist-info/METADATA
rorf-0.1.3.dist-info/WHEEL
rorf-0.1.3.dist-info/RECORD
