Metadata-Version: 2.1
Name: rorf
Version: 0.1.3
Summary: 
Author: Tze-Yang Tung
Author-email: r0ymanesco@gmail.com
Requires-Python: >=3.10,<3.12
Classifier: Programming Language :: Python :: 3
Classifier: Programming Language :: Python :: 3.10
Classifier: Programming Language :: Python :: 3.11
Requires-Dist: accelerate (>=0.34.2,<0.35.0)
Requires-Dist: click (>=8.1.7,<9.0.0)
Requires-Dist: datasets (>=3.0.0,<4.0.0)
Requires-Dist: einops (>=0.8.0,<0.9.0)
Requires-Dist: huggingface-hub (>=0.25.1,<0.26.0)
Requires-Dist: matplotlib (>=3.9.2,<4.0.0)
Requires-Dist: numpy (>=2.1.1,<3.0.0)
Requires-Dist: openai (>=1.47.1,<2.0.0)
Requires-Dist: pandas (>=2.2.3,<3.0.0)
Requires-Dist: python-dotenv (>=1.0.1,<2.0.0)
Requires-Dist: scikit-learn (>=1.5.2,<2.0.0)
Requires-Dist: tiktoken (>=0.7.0,<0.8.0)
Requires-Dist: torch (>=2.4.1,<3.0.0)
Requires-Dist: transformers (>=4.44.2,<5.0.0)
Requires-Dist: voyageai (>=0.2.3,<0.3.0)
Requires-Dist: wandb (>=0.16.4,<0.17.0)
